recml/__init__.py
recml/core/__init__.py
recml/core/data/iterator.py
recml/core/data/preprocessing.py
recml/core/data/tf_dataset_factory.py
recml/core/metrics/__init__.py
recml/core/metrics/base_metrics.py
recml/core/metrics/base_metrics_test.py
recml/core/metrics/confusion_metrics.py
recml/core/metrics/confusion_metrics_test.py
recml/core/metrics/mean_metrics.py
recml/core/metrics/mean_metrics_test.py
recml/core/metrics/reduction_metrics.py
recml/core/metrics/reduction_metrics_test.py
recml/core/metrics/tools.py
recml/core/training/core.py
recml/core/training/jax.py
recml/core/training/jax_quality_test.py
recml/core/training/jax_test.py
recml/core/training/optax_factory.py
recml/core/training/optax_factory_test.py
recml/core/training/partitioning.py
recml/core/training/partitioning_test.py
recml/core/utils/__init__.py
recml/core/utils/config.py
recml/core/utils/config_test.py
recml/core/utils/types.py
recml/core/utils/types_test.py
recml/layers/keras/bert4rec.py
recml/layers/keras/bert4rec_test.py
recml/layers/keras/hstu.py
recml/layers/keras/hstu_test.py
recml/layers/keras/mamba.py
recml/layers/keras/mamba_test.py
recml/layers/keras/sasrec.py
recml/layers/keras/sasrec_test.py
recml/layers/keras/utils.py
recml/layers/keras/utils_test.py
recml-0.1.1.dist-info/licenses/LICENSE
recml-0.1.1.dist-info/METADATA
recml-0.1.1.dist-info/WHEEL
recml-0.1.1.dist-info/top_level.txt
recml-0.1.1.dist-info/RECORD
