Metadata-Version: 2.4
Name: recml
Version: 0.1.1
Summary: RecML is envisioned as a high-performance, large-scale deep learning recommender system library optimized for Cloud TPUs
Requires-Python: >=3.12
License-File: LICENSE
Dynamic: license-file
